dyn_import_utils/__init__.py
dyn_import_utils/dyn_import_utils.py
dyn_import_utils-0.3.0.dist-info/LICENSE
dyn_import_utils-0.3.0.dist-info/METADATA
dyn_import_utils-0.3.0.dist-info/WHEEL
dyn_import_utils-0.3.0.dist-info/top_level.txt
dyn_import_utils-0.3.0.dist-info/RECORD
