Metadata-Version: 2.1
Name: dyn-import-utils
Version: 0.3.0
Summary: A simple package for dynamic imports
Home-page: UNKNOWN
Author: Your Name
Author-email: your.email@example.com
License: MIT
Platform: UNKNOWN
Classifier: Programming Language :: Python :: 3
Classifier: License :: OSI Approved :: MIT License
Classifier: Operating System :: OS Independent
Requires-Python: >=3.6
License-File: LICENSE
